poseinterface/__init__.py
poseinterface-0.0.1.dist-info/LICENSE
poseinterface-0.0.1.dist-info/METADATA
poseinterface-0.0.1.dist-info/WHEEL
poseinterface-0.0.1.dist-info/top_level.txt
poseinterface-0.0.1.dist-info/RECORD
